ptflutter/__init__.py
ptflutter/__main__.py
ptflutter/config/config_cmd.py
ptflutter/core/command.py
ptflutter/core/constants.py
ptflutter/core/model.py
ptflutter/create/create_cmd.py
ptflutter/figma/generate_text.py
ptflutter/generate/generate_image_cmd.py
ptflutter/generate/generate_localization_cmd.py
ptflutter/generate/generate_object_mapper_cmd.py
ptflutter/generate/generate_stream_debug.py
ptflutter/generate/sync_cmd.py
ptflutter/rename/config.py
ptflutter/rename/rename_cmd.py
ptflutter/template/template.py
ptflutter/template/template_cmd.py
ptflutter/template/template_mobx.py
ptflutter/usecase/usecase_cmd.py
ptflutter/utils/dart_helpers.py
ptflutter/utils/file_helpers.py
ptflutter/utils/file_replace.py
ptflutter/utils/intellij.py
ptflutter/utils/json_helpers.py
ptflutter/utils/pb.py
ptflutter/utils/str_helpers.py
ptflutter/utils/utils.py
ptflutter_templates/__init__.py
ptflutter_templates/base/assembler.dart
ptflutter_templates/base/binding.dart
ptflutter_templates/base/navigator.dart
ptflutter_templates/base/navigator_mock.dart
ptflutter_templates/base/usecase.dart
ptflutter_templates/base/usecase_mock.dart
ptflutter_templates/base/view.dart
ptflutter_templates/base/viewmodel.dart
ptflutter_templates/base/viewmodel_test.dart
ptflutter_templates/base_mobx/navigator.dart
ptflutter_templates/base_mobx/navigator_mock.dart
ptflutter_templates/base_mobx/suc.dart
ptflutter_templates/base_mobx/suc_mock.dart
ptflutter_templates/base_mobx/view.dart
ptflutter_templates/base_mobx/viewmodel.dart
ptflutter_templates/base_mobx/viewmodel_test.dart
ptflutter_templates/commands/api.dart
ptflutter_templates/commands/bindviewmodel.dart
ptflutter_templates/commands/json.dart
ptflutter_templates/commands/mock.dart
ptflutter_templates/commands/to_string.dart
ptflutter_templates/commands/unit_test.dart
ptflutter_templates/gen/entities.dart
ptflutter_templates/gen/i18n.dart
ptflutter_templates/gen/images.dart
ptflutter_templates/gen/rx_debug.dart
ptflutter-1.0.1.dist-info/LICENSE
ptflutter-1.0.1.dist-info/METADATA
ptflutter-1.0.1.dist-info/WHEEL
ptflutter-1.0.1.dist-info/entry_points.txt
ptflutter-1.0.1.dist-info/top_level.txt
ptflutter-1.0.1.dist-info/RECORD
