Metadata-Version: 2.1
Name: ptflutter
Version: 1.0.1
Summary: A code generator for Flutter
Home-page: https://github.com/tien-px/pt_flutter_tools
Author: Pham Xuan Tien
Author-email: tienpx.x.x@gmail.com
License: MIT
Platform: UNKNOWN
Classifier: Programming Language :: Python :: 3
Classifier: License :: OSI Approved :: MIT License
Classifier: Operating System :: OS Independent
Requires-Python: >=3
License-File: LICENSE
Requires-Dist: clipboard (>=0.0.4)
Requires-Dist: PyYAML (>=6.0.0)
Requires-Dist: cssutils (>=2.2.0)
Requires-Dist: Jinja2 (>=2.10)
Requires-Dist: arghandler (>=1.2)
